act_police_archiver/__init__.py
act_police_archiver/__main__.py
act_police_archiver/errors.py
act_police_archiver-1.0.2.dist-info/LICENSE
act_police_archiver-1.0.2.dist-info/WHEEL
act_police_archiver-1.0.2.dist-info/METADATA
act_police_archiver-1.0.2.dist-info/RECORD
